<?xml version="1.0" encoding="UTF-8"?>
<Documento xmlns="http://www.tredicom.com/ConfirmacionOrdenCompra" xmlns:xsd="http://www.w3.org/2001/XMLSchema">
  <Control>
    <CIN Emisor="HELVEXCIN" Receptor="GILSA_SCI_01" FechaCreacionDocumento="2018-05-28T12:28:10" Bandera="T" Version="1.0" NumDocumento="10002157"/>
    <SCI TipoDocumento="OC" Distribuidor="GILSA_SCI_01" Proveedor="HELVEX_SCI"/>
  </Control>
  <Cabecera>
    <CCO PropositoTransaccion="OR" TipoConfirmacion="AT" NumeroOrdenCompra="4500110171" FechaOrdenCompra="2018-05-26" NumeroPedidoProveedor="871180" FechaConfirmacion="2018-05-28" FechaEntregaDistribuidor="2018-05-26" FechaEntregaProveedor="2018-05-26" TextoLibreOrden="PEDIDO CREADO EXITOSAMENTE"/>
  </Cabecera>
  <Detalle>
    <ART Linea="10" CantidadOrdenada="2.000" UDM="PZ" NumArtD="04-059" NumArtP="TH-059" Descripcion="04 TH-059 CONTRA CON REJILLA P/LAV.CROMO" PrecioUnitario="476.04">
      <CAR EstatusArticulo="AA" Cantidad="2.000" CantidadBackorder="0" FechaEntregaArt="2018-06-02"/>
    </ART>
  </Detalle>
  <Resumen>
    <RES TotCantidadConfirmada="952.08"/>
  </Resumen>
</Documento>
